{
"HorizonLayout":[
{
"isSafeArea":false,
"showSearch":false,
"usePrimaryColor":true,
"enableBackground":false,
"productType":true,
"borderInput":false,
"title":"",
"type":"typewriter",
"backgroundColor":"FF010101",
"textColor":"FFFFFFFF",
"alignment":"center",
"fontWeight":300,
"fontSize":12.5,
"textOpacity":1,
"marginLeft":0,
"marginRight":0,
"marginBottom":0,
"marginTop":0,
"paddingLeft":5,
"paddingRight":15,
"paddingTop":0,
"paddingBottom":0,
"height":24,
"rotate":["Buy Any 3 Product & Get FLAT 15% Extra Discount On Checkout"],
"minWidth":0,
"backgroundGradientColor":[],
"font":"Roboto",
"layout":"header_text"
},
{
"image":"https://raw.githubusercontent.com/fluxbuilder/images/main/2025/12/91b04996b67f/1765263314402.png",
"layout":"logo",
"opacity":1,
"cartIcon":{
"name":"shopping_cart",
"fontFamily":"CupertinoIcons"
},
"iconSize":24,
"logoSize":41,
"menuIcon":{
"name":"blur_on",
"fontFamily":"MaterialIcons"
},
"showCart":true,
"showLogo":false,
"showMenu":false,
"iconRadius":6,
"showSearch":true,
"textConfig":{
"x":-0.9,
"y":0,
"text":"K Store",
"color":"#3FC1BE",
"fontSize":20,
"fontFamily":"Roboto",
"enableShadow":false
},
"iconOpacity":0,
"productType":true,
"showBadgeCart":false,
"iconSpreadRadius":0,
"showNotification":true
},
{
"fit":"fitWidth",
"items":[
{
"type":"image",
"image":"https://k-linen.com/cdn/shop/files/e2ccaa2d-1686-4f50-ba9d-45c40a4e40b7_4100x.jpg",
"video":"",
"products":[],
"productLength":3,
"showSubcategory":false,
"bannerWithProduct":false,
"defaultShowProduct":false
}
],
"design":"default",
"height":0.77,
"isBlur":false,
"layout":"bannerImage",
"radius":0,
"padding":0,
"autoPlay":false,
"isSlider":true,
"parallax":false,
"upHeight":0,
"isSoundOn":false,
"marginTop":5,
"marginLeft":0,
"showNumber":false,
"marginRight":0,
"intervalTime":3,
"isHorizontal":false,
"marginBottom":0,
"autoPlayVideo":false,
"numberPadding":{
"end":0,
"top":15,
"start":0,
"bottom":0
},
"showIndicator":true,
"showBackground":false,
"numberAlignment":{
"value":"topEnd"
},
"enableBackground":false,
"indicatorPadding":{
"end":0,
"top":0,
"start":0,
"bottom":12
},
"pageIndicatorType":"line",
"indicatorAlignment":{
"value":"bottomCenter"
},
"parallaxImageRatio":1.2,
"enableTimeIndicator":true,
"doubleTapToFullScreen":false
},
{
"size":1,
"type":"image",
"wrap":false,
"items":[
{
"tag":null,
"name":null,
"image":"https://raw.githubusercontent.com/fluxbuilder/images/main/2025/12/91b04996b67f/1765261925931.png",
"order":null,
"title":"Bedding",
"colors":null,
"onSale":false,
"orderby":null,
"category":"gid://shopify/Collection/288342278338",
"featured":false,
"showText":true,
"description":null,
"productType":false,
"originalColor":true,
"backgroundColor":null,
"showDescription":false,
"keepDefaultTitle":false,
"productListAnimationConfig":null
},
{
"tag":null,
"name":null,
"image":"https://raw.githubusercontent.com/fluxbuilder/images/main/2025/12/91b04996b67f/1765261941911.png",
"order":null,
"title":"Fitted Sheet",
"colors":null,
"onSale":false,
"orderby":null,
"category":"gid://shopify/Collection/288342638786",
"featured":false,
"showText":true,
"description":null,
"productType":false,
"originalColor":true,
"backgroundColor":null,
"showDescription":false,
"keepDefaultTitle":false,
"productListAnimationConfig":null
},
{
"tag":null,
"name":null,
"image":"https://raw.githubusercontent.com/fluxbuilder/images/main/2025/12/91b04996b67f/1765200346713.png",
"order":null,
"title":"Sofa Cover",
"colors":null,
"onSale":false,
"orderby":null,
"category":"gid://shopify/Collection/288343064770",
"featured":false,
"showText":true,
"description":null,
"productType":false,
"originalColor":true,
"backgroundColor":null,
"showDescription":false,
"keepDefaultTitle":false,
"productListAnimationConfig":null
},
{
"tag":null,
"name":null,
"image":"https://raw.githubusercontent.com/fluxbuilder/images/main/2025/12/91b04996b67f/1765261963671.png",
"order":null,
"title":"Cushion Covers",
"colors":null,
"onSale":false,
"orderby":null,
"category":"gid://shopify/Collection/288342540482",
"featured":false,
"showText":true,
"description":null,
"productType":false,
"originalColor":false,
"backgroundColor":null,
"showDescription":false,
"keepDefaultTitle":false,
"productListAnimationConfig":null
},
{
"tag":null,
"name":null,
"image":"https://raw.githubusercontent.com/fluxbuilder/images/main/2025/12/91b04996b67f/1765261990425.png",
"order":null,
"title":"Bath",
"colors":null,
"onSale":false,
"orderby":null,
"category":"gid://shopify/Collection/288342147266",
"featured":false,
"showText":true,
"description":null,
"productType":false,
"originalColor":false,
"backgroundColor":null,
"showDescription":false,
"keepDefaultTitle":false,
"productListAnimationConfig":null
},
{
"tag":null,
"name":null,
"image":"https://raw.githubusercontent.com/fluxbuilder/images/main/2025/12/91b04996b67f/1765262051335.png",
"order":null,
"title":"Accessories",
"colors":null,
"onSale":false,
"orderby":null,
"category":"gid://shopify/Collection/288342114498",
"featured":false,
"showText":true,
"description":null,
"productType":false,
"originalColor":false,
"backgroundColor":null,
"showDescription":false,
"keepDefaultTitle":false,
"productListAnimationConfig":null
},
{
"tag":null,
"name":null,
"image":"https://raw.githubusercontent.com/fluxbuilder/images/main/2025/12/91b04996b67f/1765262067659.png",
"order":null,
"title":"Clothing",
"colors":null,
"onSale":false,
"orderby":null,
"category":"gid://shopify/Collection/450409955616",
"featured":false,
"showText":true,
"description":null,
"productType":false,
"originalColor":false,
"backgroundColor":null,
"showDescription":false,
"keepDefaultTitle":false,
"productListAnimationConfig":null
},
{
"tag":null,
"name":null,
"image":"https://raw.githubusercontent.com/fluxbuilder/images/main/2025/12/91b04996b67f/1765262120974.png",
"order":null,
"title":"Blankets",
"colors":null,
"onSale":false,
"orderby":null,
"category":"gid://shopify/Collection/288342343874",
"featured":false,
"showText":true,
"description":null,
"productType":false,
"originalColor":false,
"backgroundColor":null,
"showDescription":false,
"keepDefaultTitle":false,
"productListAnimationConfig":null
},
{
"tag":null,
"name":null,
"image":"https://raw.githubusercontent.com/fluxbuilder/images/main/2025/12/91b04996b67f/1765262157449.png",
"order":"desc",
"title":"Fabric",
"colors":null,
"onSale":false,
"orderby":"date",
"category":"gid://shopify/Collection/508687974688",
"featured":false,
"showText":true,
"description":null,
"productType":false,
"originalColor":false,
"backgroundColor":null,
"showDescription":false,
"keepDefaultTitle":false,
"productListAnimationConfig":null
}
],
"border":0,
"layout":"category",
"radius":0,
"shadow":null,
"columns":3,
"marginX":0,
"marginY":5,
"spacing":12,
"itemSize":{
"width":120,
"height":140
},
"paddingX":0,
"paddingY":0,
"hideTitle":false,
"marginTop":0,
"marginLeft":0,
"imageBoxFit":"fitHeight",
"marginRight":0,
"enableBorder":false,
"imageSpacing":0,
"marginBottom":6,
"noBackground":false,
"gradientStyle":false,
"labelFontSize":14,
"originalColor":false,
"separateWidth":24,
"textAlignment":"topCenter",
"horizontalItem":false,
"animationConfig":null,
"enableBackground":null,
"imageBorderStyle":"solid",
"categoryMenuShowDepth":false,
"productCategoryMenuStyle":"menu",
"allowFilterMultipleCategory":false
},
{
"name":"Fresh Looks for Your Bed",
"rows":1,
"limit":33,
"layout":"quiltedGridTile",
"onSale":false,
"columns":3,
"hMargin":6,
"useSort":false,
"vMargin":0,
"category":"gid://shopify/Collection/288342278338",
"hPadding":6,
"parallax":false,
"vPadding":2,
"boxShadow":{
"x":8,
"y":4,
"blurRadius":15.01010101010101,
"colorOpacity":0.1,
"spreadRadius":0
},
"hidePrice":false,
"hideStore":false,
"hideTitle":false,
"showHeart":false,
"cardDesign":"quiltedCard",
"imageRatio":1.2,
"isSnapping":false,
"hideAddress":false,
"imageBoxfit":"cover",
"borderRadius":3,
"enableRating":true,
"showCartIcon":true,
"showCategory":false,
"showQuantity":false,
"showCountDown":false,
"showOnlyImage":false,
"advancedParams":{
},
"cartIconRadius":9,
"showCartButton":false,
"showListingType":true,
"showPhoneNumber":false,
"showStockStatus":true,
"backgroundRadius":10,
"enableAutoSliding":false,
"showCartIconColor":false,
"useCircularRadius":true,
"parallaxImageRatio":1.2,
"enableBottomAddToCart":true,
"productListItemHeight":125,
"cartButtonQuantitySize":40,
"hideEmptyProductLayout":false,
"showProductCardCategory":false,
"hideEmptyProductListRating":false,
"showCartButtonWithQuantity":false
},
{
"name":"Terry Sofa Covers",
"rows":1,
"layout":"threeColumn",
"onSale":false,
"columns":0,
"hMargin":6,
"useSort":false,
"vMargin":0,
"category":"gid://shopify/Collection/288343195842",
"featured":false,
"hPadding":9,
"parallax":false,
"vPadding":2,
"hidePrice":false,
"hideStore":false,
"hideTitle":false,
"showHeart":false,
"cardDesign":"glass",
"imageRatio":1.2,
"isSnapping":false,
"paddingBGP":{
"top":36.58208631931391,
"left":0,
"right":0,
"bottom":0
},
"spaceWidth":138.2,
"hideAddress":false,
"imageBoxfit":"fill",
"borderRadius":21,
"enableRating":true,
"showCartIcon":true,
"showCategory":false,
"showQuantity":false,
"showCountDown":false,
"showOnlyImage":false,
"advancedParams":{
},
"cartIconRadius":9,
"showCartButton":false,
"backgroundColor":"ff885819",
"backgroundImage":"https://trello.com/1/cards/6937edaa84fd80c4d8eb3cb2/attachments/6937edabd8924d6c38237a8b/download/terry.jpg",
"showListingType":true,
"showPhoneNumber":false,
"showStockStatus":true,
"backgroundBoxFit":"cover",
"backgroundHeight":331.8642064144734,
"backgroundRadius":34,
"enableAutoSliding":false,
"showCartIconColor":false,
"useCircularRadius":true,
"parallaxImageRatio":1.2,
"enableBottomAddToCart":false,
"productListItemHeight":125,
"cartButtonQuantitySize":40,
"hideEmptyProductLayout":false,
"showProductCardCategory":false,
"hideEmptyProductListRating":false,
"showCartButtonWithQuantity":false
},
{
"name":"Perfect Fit for Your Bed",
"rows":1,
"layout":"threeColumn",
"onSale":false,
"columns":3,
"hMargin":5,
"useSort":false,
"vMargin":5,
"category":"gid://shopify/Collection/288342638786",
"hPadding":5,
"parallax":false,
"vPadding":0,
"boxShadow":{
"x":2,
"y":2,
"blurRadius":3.0101010101010104,
"colorOpacity":0.1,
"spreadRadius":10
},
"hidePrice":false,
"hideStore":false,
"hideTitle":false,
"marginBGP":{
"top":2.1,
"left":0,
"right":0,
"bottom":0
},
"showHeart":true,
"cardDesign":"flatSimple",
"imageRatio":0.8,
"imageWidth":130.39847400700933,
"isSnapping":false,
"hideAddress":false,
"imageBoxfit":"fitWidth",
"borderRadius":10,
"enableRating":false,
"showCartIcon":true,
"showCategory":false,
"showQuantity":false,
"showCountDown":false,
"showOnlyImage":false,
"advancedParams":{
},
"cartIconRadius":9,
"showCartButton":false,
"backgroundColor":"fffffbef",
"showListingType":true,
"showPhoneNumber":false,
"showStockStatus":false,
"backgroundHeight":230,
"backgroundRadius":0,
"enableAutoSliding":true,
"showCartIconColor":false,
"useCircularRadius":true,
"parallaxImageRatio":1.2,
"durationAutoSliding":57,
"enableBottomAddToCart":true,
"productListItemHeight":125,
"cartButtonQuantitySize":40,
"hideEmptyProductLayout":false,
"showProductCardCategory":false,
"hideEmptyProductListRating":false,
"showCartButtonWithQuantity":false
},
{
"name":"Refresh Your Bath",
"rows":1,
"limit":25,
"layout":"twoColumn",
"onSale":false,
"slider":{
"type":"contentBetweenCard",
"hideTag":true,
"autoPlay":true,
"colorTag":null,
"borderRadius":3,
"colorTextTag":null,
"limitIndicator":8,
"paddingContent":null,
"borderRadiusTag":5,
"pageIndicatorType":"line",
"secondsAutoSliding":null
},
"columns":0,
"hMargin":6,
"useSort":false,
"vMargin":0,
"category":"gid://shopify/Collection/288342147266",
"featured":false,
"hPadding":0,
"parallax":false,
"vPadding":0,
"hidePrice":false,
"hideStore":false,
"hideTitle":false,
"showHeart":false,
"cardDesign":"glass",
"imageRatio":0.9,
"isSnapping":true,
"hideAddress":false,
"imageBoxfit":"fitWidth",
"borderRadius":3,
"enableRating":false,
"showCartIcon":true,
"showCategory":false,
"showQuantity":false,
"showCountDown":false,
"showOnlyImage":false,
"advancedParams":{
},
"cartIconRadius":20,
"showCartButton":false,
"showListingType":true,
"showPhoneNumber":false,
"showStockStatus":false,
"backgroundBoxFit":"cover",
"backgroundRadius":10,
"enableAutoSliding":false,
"showCartIconColor":true,
"useCircularRadius":true,
"parallaxImageRatio":1.2,
"enableBottomAddToCart":false,
"productListItemHeight":125,
"cartButtonQuantitySize":40,
"hideEmptyProductLayout":false,
"showProductCardCategory":false,
"hideEmptyProductListRating":false,
"showCartButtonWithQuantity":false
},
{
"name":"Just for Her",
"rows":1,
"limit":17,
"order":"desc",
"layout":"twoColumn",
"onSale":false,
"columns":0,
"hMargin":6,
"orderby":"date",
"useSort":false,
"vMargin":20,
"category":"gid://shopify/Collection/288343359682",
"featured":false,
"hPadding":8,
"parallax":false,
"vPadding":8,
"boxShadow":{
"x":0,
"y":10,
"blurRadius":10,
"colorOpacity":0.1,
"spreadRadius":10
},
"hidePrice":false,
"hideStore":false,
"hideTitle":false,
"showHeart":false,
"cardDesign":"card",
"imageRatio":0.7625027813488929,
"isSnapping":true,
"spaceWidth":12.608443859011626,
"hideAddress":false,
"imageBoxfit":"fitWidth",
"borderRadius":9,
"enableRating":false,
"showCartIcon":true,
"showCategory":false,
"showQuantity":false,
"showCountDown":false,
"showOnlyImage":false,
"advancedParams":{
},
"cartIconRadius":9,
"showCartButton":false,
"backgroundColor":"5bffcff1",
"backgroundImage":"https://raw.githubusercontent.com/fluxbuilder/images/main/2025/12/91b04996b67f/1765281485845.jpg",
"showListingType":true,
"showPhoneNumber":false,
"showStockStatus":false,
"backgroundHeight":315.4225903888082,
"backgroundRadius":0,
"enableAutoSliding":false,
"showCartIconColor":false,
"useCircularRadius":true,
"parallaxImageRatio":1.2,
"enableBottomAddToCart":false,
"productListItemHeight":92,
"cartButtonQuantitySize":40,
"hideEmptyProductLayout":false,
"showProductCardCategory":false,
"hideEmptyProductListRating":false,
"showCartButtonWithQuantity":false
},
{
"name":"Cozy Blankets",
"rows":1,
"limit":20,
"order":"asc",
"layout":"twoColumn",
"onSale":false,
"columns":0,
"hMargin":6,
"orderby":"date",
"useSort":false,
"vMargin":0,
"category":"gid://shopify/Collection/288342343874",
"featured":false,
"hPadding":8,
"parallax":false,
"vPadding":0,
"boxShadow":{
"x":0,
"y":10,
"blurRadius":10,
"colorOpacity":0.1,
"spreadRadius":10
},
"hidePrice":false,
"hideStore":false,
"hideTitle":false,
"showHeart":false,
"cardDesign":"card",
"imageRatio":1.032813970726657,
"isSnapping":false,
"hideAddress":false,
"imageBoxfit":"fitWidth",
"borderRadius":15,
"enableRating":false,
"showCartIcon":false,
"showCategory":false,
"showQuantity":false,
"showCountDown":false,
"showOnlyImage":false,
"advancedParams":{
},
"cartIconRadius":20,
"showCartButton":false,
"showListingType":true,
"showPhoneNumber":false,
"showStockStatus":false,
"backgroundBoxFit":"fitWidth",
"backgroundRadius":10,
"enableAutoSliding":false,
"showCartIconColor":true,
"useCircularRadius":true,
"parallaxImageRatio":1.2,
"enableBottomAddToCart":false,
"productListItemHeight":125,
"cartButtonQuantitySize":40,
"hideEmptyProductLayout":false,
"showProductCardCategory":false,
"hideEmptyProductListRating":false,
"showCartButtonWithQuantity":false
},
{
"font":"Roboto",
"type":"static",
"title":"Join our social community",
"height":30,
"layout":"header_text",
"rotate":[],
"fontSize":18,
"minWidth":0,
"alignment":"bottomRight",
"marginTop":15,
"textColor":"ff000000",
"fontWeight":300,
"isSafeArea":false,
"marginLeft":0,
"paddingTop":0,
"showSearch":false,
"borderInput":false,
"marginRight":0,
"paddingLeft":15,
"productType":true,
"textOpacity":0.8,
"marginBottom":0,
"paddingRight":15,
"paddingBottom":0,
"usePrimaryColor":true,
"enableBackground":false,
"backgroundGradientColor":[]
},
{
"items":[
{
"image":"https://trello.com/1/cards/60efb9b97be65b6792f8f836/attachments/61960e768e015a78a380b2fc/previews/61960e768e015a78a380b30d/download/instagram.png",
"width":32,
"height":32,
"navigator":{
"key":"AcGHFQwCfN",
"url_launch":"https://www.instagram.com/klinenpk/?hl=en"
},
"marginLeft":15,
"marginRight":5,
"useMaxWidth":false,
"borderRadius":2,
"textFontSize":14
},
{
"image":"https://trello.com/1/cards/60efb9b97be65b6792f8f836/attachments/61960e7449c64e503c3ba8e7/previews/61960e7549c64e503c3ba901/download/facebook.png",
"width":32,
"height":32,
"navigator":{
"key":"IdYiTmvhfl",
"url_launch":"https://www.facebook.com/KLinenpk/"
},
"marginLeft":0,
"marginRight":5,
"useMaxWidth":false,
"borderRadius":2,
"textFontSize":14
},
{
"image":"https://trello.com/1/cards/60efb9b97be65b6792f8f836/attachments/61961042c90d756e6739284d/previews/61961042c90d756e67392932/download/youtube.png",
"width":32,
"height":32,
"navigator":{
"key":"PrRtqWSxCh",
"url_launch":"https://www.youtube.com/@k-linen"
},
"marginLeft":0,
"marginRight":10,
"useMaxWidth":false,
"borderRadius":2,
"textFontSize":14
}
],
"layout":"button",
"alignment":"topRight",
"marginTop":0,
"marginBottom":5,
"enableBackground":false
},
{
"fit":"fitHeight",
"items":[
{
"type":"image",
"image":"https://trello.com/1/cards/6937edaa84fd80c4d8eb3cb2/attachments/69380bbee666b5d87b28853b/download/New_Project_(41).jpg",
"video":"",
"radius":0,
"padding":0,
"products":[],
"productLength":3,
"showSubcategory":false,
"bannerWithProduct":false,
"defaultShowProduct":false
}
],
"design":"static",
"layout":"bannerImage",
"radius":32.4,
"padding":15.1,
"parallax":false,
"marginTop":0,
"marginLeft":0,
"marginRight":0,
"isHorizontal":false,
"marginBottom":0,
"numberPadding":{
"end":0,
"top":15,
"start":0,
"bottom":0
},
"numberAlignment":{
"value":"topEnd"
},
"enableBackground":false,
"indicatorPadding":{
"end":0,
"top":0,
"start":0,
"bottom":12
},
"indicatorAlignment":{
"value":"bottomCenter"
},
"parallaxImageRatio":1.2
}
],
"Setting":{
"FontHeader":"Alata",
"StickyHeader":false,
"TabBarConfig":{
"color":null,
"enable":true,
"iconSize":22,
"colorCart":null,
"colorIcon":"ffa6b0b3",
"marginTop":0,
"isSafeArea":true,
"marginLeft":0,
"paddingTop":0,
"enableOnTop":false,
"marginRight":0,
"paddingLeft":0,
"marginBottom":0,
"paddingRight":0,
"showFloating":true,
"showMinimize":false,
"enableDivider":true,
"paddingBottom":0,
"radiusTopLeft":0,
"TabBarFloating":{
"color":"ff1f4751",
"width":50,
"height":50,
"radius":50,
"location":null,
"position":2,
"elevation":2,
"isCoverMode":false,
"notchMargin":4,
"floatingType":"circle"
},
"indicatorStyle":"none",
"radiusTopRight":0,
"TabBarIndicator":{
"color":null,
"height":0,
"radius":0,
"strokeWidth":0,
"tabPosition":"bottom",
"paintingStyle":"fill",
"topLeftRadius":0,
"topRightRadius":0,
"verticalPadding":0,
"bottomLeftRadius":0,
"bottomRightRadius":0,
"horizontalPadding":0,
"distanceFromCenter":0
},
"colorActiveIcon":"ff1f4751",
"alwaysShowTabBar":false,
"radiusBottomLeft":0,
"showFloatingClip":true,
"radiusBottomRight":0
},
"ProductDetail":"gallerySlider",
"ProductListLayout":"list"
},
"TabBar":[
{
"key":"EtaiBNIRHW",
"pos":100,
"icon":"home",
"layout":"home",
"defaultTab":false,
"fontFamily":"CupertinoIcons",
"fullscreen":false,
"showOriginalColor":false
},
{
"key":"sGBGoGnmSR",
"pos":200,
"icon":"square_split_2x2",
"layout":"category",
"visible":true,
"parallax":false,
"categories":["gid://shopify/Collection/288342442178",
"gid://shopify/Collection/288342311106",
"gid://shopify/Collection/288673333442",
"gid://shopify/Collection/292253925570",
"gid://shopify/Collection/288342573250",
"gid://shopify/Collection/288343326914",
"gid://shopify/Collection/288342769858",
"gid://shopify/Collection/465188552992",
"gid://shopify/Collection/288342835394",
"gid://shopify/Collection/288343163074",
"gid://shopify/Collection/293419417794",
"gid://shopify/Collection/288342802626",
"gid://shopify/Collection/429370835232",
"gid://shopify/Collection/288343294146",
"gid://shopify/Collection/288377077954",
"gid://shopify/Collection/288343425218",
"gid://shopify/Collection/288343195842",
"gid://shopify/Collection/437788541216",
"gid://shopify/Collection/486166462752",
"gid://shopify/Collection/476167242016",
"gid://shopify/Collection/502155018528",
"gid://shopify/Collection/503100735776",
"gid://shopify/Collection/288343392450",
"gid://shopify/Collection/492723863840",
"gid://shopify/Collection/492723929376",
"gid://shopify/Collection/492723962144",
"gid://shopify/Collection/492723994912",
"gid://shopify/Collection/493157417248",
"gid://shopify/Collection/476658204960",
"gid://shopify/Collection/288342212802",
"gid://shopify/Collection/288342180034",
"gid://shopify/Collection/288343228610",
"gid://shopify/Collection/288342999234",
"gid://shopify/Collection/288342376642",
"gid://shopify/Collection/288342474946",
"gid://shopify/Collection/462711882016",
"gid://shopify/Collection/448986906912",
"gid://shopify/Collection/288342704322",
"gid://shopify/Collection/288343032002",
"gid://shopify/Collection/288343130306",
"gid://shopify/Collection/429156499744",
"gid://shopify/Collection/288342966466",
"gid://shopify/Collection/293265834178",
"gid://shopify/Collection/288342737090",
"gid://shopify/Collection/288343457986",
"gid://shopify/Collection/470081339680",
"gid://shopify/Collection/288342343874",
"gid://shopify/Collection/288343261378",
"gid://shopify/Collection/508687974688"],
"defaultTab":false,
"fontFamily":"CupertinoIcons",
"fullscreen":false,
"showQRCode":true,
"showSearch":true,
"categoryLayout":"sideMenu",
"showOriginalColor":false,
"parallaxImageRatio":1.2
},
{
"key":"LeztJLuFjN",
"pos":300,
"icon":"search",
"layout":"search",
"visible":true,
"defaultTab":false,
"fontFamily":"CupertinoIcons",
"fullscreen":false,
"showQRCode":true,
"showOriginalColor":false
},
{
"key":"XRrbpaQcth",
"pos":400,
"icon":"bag",
"layout":"cart",
"fontFamily":"CupertinoIcons",
"categoryLayout":"cart"
},
{
"key":"CUxNtUiSZH",
"pos":500,
"icon":"person",
"layout":"profile",
"visible":true,
"settings":["biometrics",
"wishlist",
"notifications",
"order"],
"styleItem":"flatShadow",
"background":"https://images.unsplash.com/photo-1528459061998-56fd57ad86e3?auto=format&fit=crop&q=80&w=3140&ixlib=rb-4.0.3&ixid=M3wxMjA3fDB8MHxwaG90by1wYWdlfHx8fGVufDB8fHx8fA%3D%3D",
"defaultTab":false,
"fontFamily":"CupertinoIcons",
"fullscreen":false,
"showBackground":true,
"showOriginalColor":false
}
],
"AppBar":{
"snap":true,
"items":[
{
"pos":100,
"icon":"person",
"size":44,
"type":"text",
"radius":0,
"fontSize":16,
"iconSize":24,
"alignment":"center",
"marginTop":0,
"fontFamily":"CupertinoIcons",
"fontWeight":"400",
"marginLeft":0,
"paddingTop":0,
"marginRight":0,
"paddingLeft":0,
"productType":true,
"spacingText":3,
"textOpacity":0.5,
"avatarRadius":100,
"marginBottom":0,
"paddingRight":0,
"paddingBottom":0,
"headerFontSize":16,
"headerFontWeight":"400",
"headerTextOpacity":0.5
}
],
"enable":false,
"pinned":true,
"floating":true,
"elevation":0,
"showOnScreens":["home"],
"alwaysShowAppBar":false
},
"Drawer":{
"key":"RizYHFFqfj",
"logo":null,
"items":[
{
"show":false,
"type":"home"
},
{
"show":false,
"type":"blog"
},
{
"show":false,
"type":"categories"
},
{
"show":false,
"type":"cart"
},
{
"show":false,
"type":"profile"
},
{
"show":false,
"type":"login"
},
{
"show":false,
"type":"category"
}
],
"enable":false,
"filter":0.1,
"logoDark":null,
"safeArea":false,
"iconColor":"ffffffff",
"textColor":"ffffffff",
"logoConfig":{
"width":150,
"boxFit":"fitWidth",
"height":38,
"marginTop":60,
"marginLeft":20,
"marginRight":0,
"marginBottom":10
},
"zoomConfig":null,
"colorFilter":"ffffffff",
"subDrawerItem":{
},
"backgroundColor":null,
"backgroundImage":"https://images.unsplash.com/photo-1547149600-a6cdf8fce60c?auto=format&fit=crop&q=80&w=2787&ixlib=rb-4.0.3&ixid=M3wxMjA3fDB8MHxwaG90by1wYWdlfHx8fGVufDB8fHx8fA%3D%3D"}}
